{"responses":{"200":{"description":"Updates the draft version","content":{"application/json":{"examples":{"200 - Updates the draft version":{"value":{"id":"app-store-version-id","app_store_state":"PREPARE_FOR_SUBMISSION","version_string":"1.2.3","release_type":"MANUAL","earliest_release_date":null}}}}}},"401":{"description":"Unauthorized","content":{"application/json":{"examples":{"401 - Unauthorized":{"value":{"code":"ERR_UNAUTHORIZED","message":"Unauthorized"}}}}}},"403":{"description":"Permission denied","content":{"application/json":{"examples":{"403 - Permission denied":{"value":{"code":"ERR_PERMISSION_DENIED","message":"Permission denied"}}}}}},"404":{"description":"No App Store version exists","content":{"application/json":{"examples":{"404 - No local app version exists for the target version_string":{"value":{"code":"ERR_APP_VERSION_NOT_FOUND","message":"Could not find related app_version: version-without-a-release"}},"404 - No App Store version exists":{"value":{"code":"ERR_APP_STORE_VERSION_NOT_FOUND","message":"ReleaseManagement::ErrorHandling::NotFound"}}}}}},"409":{"description":"Draft version is not in an editable state","content":{"application/json":{"examples":{"409 - Draft version is not in an editable state":{"value":{"code":"ERR_CONFLICTS_WITH_CURRENT_STATE","message":"The App Store version's status is not in an editable state.","details":"Either complete the process in App Store Connect or cancel any outstanding reviews so that Release Management can continue the release flow here: https://appstoreconnect.apple.com/apps/1234/distribution/ios/version/inflight."}}}}}},"412":{"description":"Standard license required","content":{"application/json":{"examples":{"412 - Standard license required":{"value":{"code":"ERR_STANDARD_LICENSE_REQUIRED","message":"This benefit requires a Standard license for the connected app."}}}}}},"500":{"description":"Internal Server Error","content":{"application/json":{"examples":{"500 - Internal Server Error":{"value":{"code":"ERR_INTERNAL","message":"Something went wrong"}}}}}}}}