{"title":"Body","body":{"content":{"application/json":{"schema":{"type":"object","properties":{"summary":{"type":"string","description":"The summary of your approval task."},"description":{"type":"string","description":"The detailed explanation of your approval task, providing additional context beyond the summary."},"assigned_user_slug":{"type":"string","description":"The user's slug to assign the approval task to."},"completed":{"type":"boolean","description":"The boolean flag of your approval task which marks it completed."}},"required":["name"]}}}}}